{
  "anchor": {},
  "http-api": {
    "hostname": "127.0.0.1",
    "port": 7007,
    "admin-dids": [
      "did:key:z6MkkNZJxrZpvd8EUX4fANTyjcGxf7KWEnViLCEcNsMd68B8",
      "did:key:z6Mkv6uUPY1qnotP2qiNhuBbft2pDguv5J6sftuWse9SvWNN"
    ]
  },
  "ipfs": {
    "mode": "bundled"
  },
  "logger": {
    "log-directory": "./log/ceramic",
    "log-level": 2,
    "log-to-files": true
  },
  "metrics": {
    "metrics-exporter-enabled": false
  },
  "network": {
    "name": "inmemory"
  },
  "node": {
    "gateway": false
  },
  "state-store": {
    "mode": "file",
    "local-directory": "/etc/ceramic/data"
  },
  "indexing": {
    "db": "sqlite:///Users/ajiteshjamulkar/Desktop/MedBlock/ceramic/ceramic-app/ceramic-indexing/ceramic.db",
    "allow-queries-before-historical-sync": true,
    "enable-historical-sync": false
  }
}